Laboratorio09/Ejercicio03/flipflopJK.v
module  FlipFlopD1b(input d,enable,reset,clk,output reg q);
    // copiado del ejercicio 1
    always @(posedge clk, posedge reset) begin  //reset asincrono
        if (reset) q = 0; // si el reset esta activado la salida se coloca en 0
        else if (enable) q = d; //si reset esta en 0 y ademas esta enable en 1, entonces deja pasar d a q
    end

endmodule


module FlipFlopJK(input wire J,K, enable, reset, clk, output wire q );

    wire d;

    assign d = ~K & q | J & ~q; // ecuacion para la entrada d del ff segun logic friday

    FlipFlopD1b FF(d,enable,reset,clk,q);

endmodule

Laboratorio09/Ejercicio03/flipflopJK_tb.v
module testbench();

    reg clk,enable,reset, j,k;
    wire q;

    FlipFlopJK FF(j,k,enable,reset,clk,q);

  initial clk = 0;

    always  #1 clk = ~clk;

    initial begin
        #1 enable =0; reset=0;j=0;k=0;
        #1 reset = 1;
        #1 reset = 0;
        #1 enable =1;
        #4 j=1;
        #4 j=0;
        #8 k=1;
        #8 k=0;
        #4 j=1;k=1;
        #14 j=0;k=0;
        #10 $finish;

    end


    initial begin
        $dumpfile("flipflopJK_tb.vcd");
        $dumpvars(0,testbench);
    end

endmodule

Laboratorio09/Ejercicio03/flipflopT_tb.vcd
$date
	Fri Oct 30 22:26:00 2020
$end
$version
	Icarus Verilog
$end
$timescale
	1ps
$end
$scope module testbench $end
$var wire 1 ! q $end
$var reg 1 " clk $end
$var reg 1 # enable $end
$var reg 1 $ j $end
$var reg 1 % k $end
$var reg 1 & reset $end
$scope module FF $end
$var wire 1 $ J $end
$var wire 1 % K $end
$var wire 1 " clk $end
$var wire 1 ' d $end
$var wire 1 # enable $end
$var wire 1 & reset $end
$var wire 1 ! q $end
$scope module FF $end
$var wire 1 " clk $end
$var wire 1 ' d $end
$var wire 1 # enable $end
$var wire 1 & reset $end
$var reg 1 ! q $end
$upscope $end
$upscope $end
$upscope $end
$enddefinitions $end
#0
$dumpvars
x'
0&
0%
0$
0#
0"
x!
$end
#1
0'
0!
1&
1"
#2
0&
0"
#3
1#
1"
#4
0"
#5
1"
#6
0"
#7
1'
1"
1$
#8
0"
#9
1!
1"
#10
0"
#11
1"
0$
#12
0"
#13
1"
#14
0"
#15
1"
#16
0"
#17
1"
#18
0"
#19
0'
1"
1%
#20
0"
#21
0!
1"
#22
0"
#23
1"
#24
0"
#25
1"
#26
0"
#27
1"
0%
#28
0"
#29
1"
#30
0"
#31
1'
1"
1$
#32
0"
#33
1!
1"
#34
0"
#35
1"
#36
0"
#37
1"
#38
0"
#39
1"
#40
0"
#41
1"
#42
0"
#43
1"
#44
0"
#45
1"
0$
