Lab03/SOP_4/SOP4.v
module SOP4();
    reg a,b,c,d;

    wire nota,notb,notc,notd;
    wire m0,m2,m3,m7,m8,m9,m11;
    wire out;
    //entradas negadas
    not n1(nota,a);
    not n2(notb,b);
    not n3(notc,c); 
    not n4(notd,d);
    //minterminos
    and a1(m0,nota,notb,notc,notd);
    and a2(m2,nota,notb,c,notd);
    and a3(m3,nota,notb,c,d);
    and a4(m7,nota,b,c,notd);
    and a5(m8,nota,b,c,d);
    and a6(m9,a,notb,notc,notd);
    and a7(m11,a,notb,c,notd);
    //suma
    or o1(out,m0,m2,m3,m7,m8,m9,m11);

    initial begin
        $display("A B C D | Y");
        $display("---------");
        $monitor("%b %b %b %b | %b", a, b,c,d, out);
        a=0;b=0;c=0;d=0;
            #1 d=1;
        #1 c=1;d=0;
        #1 d=1;
        #1 b=1;c=0;d=0;
        #1  d=1;
        #1  c=1;d=0;
        #1  d=1;
        #1 a=1;b=0;c=0;d=0;
        #1 d=1;
        #1 c=1;d=0;
        #1 d=1;
        #1 b=1;c=0;d=0;
        #1  d=1;
        #1  c=1;d=0;
        #1  d=1;
        #1 $finish;
    end
    initial 
    begin
      $dumpfile("SOP4_tb.vcd"); 
      $dumpvars(0,SOP4);
    end 
endmodule

Laboratorio03/SOP_4/SOP4_tb.vcd
$date
	Sat Aug 01 10:19:06 2020
$end
$version
	Icarus Verilog
$end
$timescale
	1ps
$end
$scope module SOP4 $end
$var wire 1 ! m0 $end
$var wire 1 " m11 $end
$var wire 1 # m2 $end
$var wire 1 $ m3 $end
$var wire 1 % m7 $end
$var wire 1 & m8 $end
$var wire 1 ' m9 $end
$var wire 1 ( nota $end
$var wire 1 ) notb $end
$var wire 1 * notc $end
$var wire 1 + notd $end
$var wire 1 , out $end
$var reg 1 - a $end
$var reg 1 . b $end
$var reg 1 / c $end
$var reg 1 0 d $end
$upscope $end
$enddefinitions $end
#0
$dumpvars
00
0/
0.
0-
1,
1+
1*
1)
1(
0'
0&
0%
0$
0#
0"
1!
$end
#1
0,
0!
0+
10
#2
1,
1#
1+
0*
00
1/
#3
0#
1$
0+
10
#4
0,
1+
0$
1*
0)
00
0/
1.
#5
0+
10
#6
1,
1%
1+
0*
00
1/
#7
0%
1&
0+
10
#8
1'
1+
1*
0&
1)
0(
00
0/
0.
1-
#9
0,
0'
0+
10
#10
1,
1"
1+
0*
00
1/
#11
0,
0"
0+
10
#12
1+
1*
0)
00
0/
1.
#13
0+
10
#14
1+
0*
00
1/
#15
0+
10
