Lab03/POS_1/POS1.v
module POS1();
    reg a,b,c;

    wire M1,M3,M6;
    wire notA,notB,notC;
    wire out;
    //negaciones de las entradas
    not N1(notA,a);
    not N2(notB,b);
    not N3(notC,c);

    // maxterminos
    or O1(M1,a,b,notC);
    or O2(M3,a,notB,notC);
    or O3(M6,notA,notB,c);
    and A1(out,M1,M3,M6);

    initial begin
        $display("A B C | Y");
        $display("---------");
        $monitor("%b %b %b |%b",a,b,c,out);
        a=0; b=0; c=0;
        #1 c=1;
        #1  b=1; c=0;
        #1 c=1;
        #1  a=1; b=0; c=0;
        #1 c=1;
        #1 b=1;c=0;
        #1 c=1;
        #1 $finish;

    end
    initial 
    begin
      $dumpfile("POS1_tb.vcd"); 
      $dumpvars(0,POS1);
    end 

endmodule

Lab03/POS_1/POS1_tb.vcd
$date
	Sat Aug 08 18:16:51 2020
$end
$version
	Icarus Verilog
$end
$timescale
	1ps
$end
$scope module POS1 $end
$var wire 1 ! M1 $end
$var wire 1 " M3 $end
$var wire 1 # M6 $end
$var wire 1 $ notA $end
$var wire 1 % notB $end
$var wire 1 & notC $end
$var wire 1 ' out $end
$var reg 1 ( a $end
$var reg 1 ) b $end
$var reg 1 * c $end
$upscope $end
$enddefinitions $end
#0
$dumpvars
0*
0)
0(
1'
1&
1%
1$
1#
1"
1!
$end
#1
0'
0!
0&
1*
#2
1'
1&
1!
0%
0*
1)
#3
0'
0"
0&
1*
#4
1'
1&
1%
1"
0$
0*
0)
1(
#5
0&
1*
#6
0'
0#
1&
0%
0*
1)
#7
1'
1#
0&
1*
