Lab03/POS_4/POS4.v
module POS4();
    reg a,b,c,d;

    wire nota,notb,notc,notd;
    wire m1,m4,m5,m9,m11,m12,m13,m14,m15;
    wire out;
    //entradas negadas
    not n1(nota,a);
    not n2(notb,b);
    not n3(notc,c); 
    not n4(notd,d);
    //maxterminos
    or O1(m1,a,b,c,notd);
    or O2(m4,a,notb,c,d);
    or O3(m5,a,notb,c,notd);
    or O4(m9,nota,b,c,notd);
    or O5(m11,nota,b,notc,notd);
    or O6(m12,nota,notb,c,d);
    or O7(m13,nota,notb,c,notd);
    or O8(m14,nota,notb,notc,d);
    or O9(m15,nota,notb,notc,notd);
    // multiplicacion
    and A1(out,m1,m4,m5,m9,m11,m12,m13,m14,m15);

    initial begin
        $display("A B C D | Y");
        $display("---------");
        $monitor("%b %b %b %b | %b", a, b,c,d, out);
        a=0;b=0;c=0;d=0;
            #1 d=1;
        #1 c=1;d=0;
        #1 d=1;
        #1 b=1;c=0;d=0;
        #1  d=1;
        #1  c=1;d=0;
        #1  d=1;
        #1 a=1;b=0;c=0;d=0;
        #1 d=1;
        #1 c=1;d=0;
        #1 d=1;
        #1 b=1;c=0;d=0;
        #1  d=1;
        #1  c=1;d=0;
        #1  d=1;
        #1 $finish;
    end
    initial 
    begin
      $dumpfile("POS4_tb.vcd"); 
      $dumpvars(0,POS4);
    end 
endmodule

Lab03/POS_4/POS4_tb.vcd
$date
	Sat Aug 01 09:35:29 2020
$end
$version
	Icarus Verilog
$end
$timescale
	1ps
$end
$scope module POS4 $end
$var wire 1 ! m1 $end
$var wire 1 " m11 $end
$var wire 1 # m12 $end
$var wire 1 $ m13 $end
$var wire 1 % m14 $end
$var wire 1 & m15 $end
$var wire 1 ' m4 $end
$var wire 1 ( m5 $end
$var wire 1 ) m9 $end
$var wire 1 * nota $end
$var wire 1 + notb $end
$var wire 1 , notc $end
$var wire 1 - notd $end
$var wire 1 . out $end
$var reg 1 / a $end
$var reg 1 0 b $end
$var reg 1 1 c $end
$var reg 1 2 d $end
$upscope $end
$enddefinitions $end
#0
$dumpvars
02
01
00
0/
1.
1-
1,
1+
1*
1)
1(
1'
1&
1%
1$
1#
1"
1!
$end
#1
0.
0!
0-
12
#2
1.
1-
1!
0,
02
11
#3
0-
12
#4
0.
1-
1(
0'
1,
0+
02
01
10
#5
0(
1'
0-
12
#6
1.
1-
1(
0,
02
11
#7
0-
12
#8
1.
1-
1,
1"
1)
1+
0*
02
01
00
1/
#9
0.
0)
0-
12
#10
1.
1-
1)
0,
02
11
#11
0.
0"
0-
12
#12
1-
1$
0#
1,
1"
0+
02
01
10
#13
0$
1#
0-
12
#14
0%
1-
1$
0,
02
11
#15
0&
1%
0-
12
