Laboratorio09/Ejercicio01/flipflop.v
module  FlipFlopD1b(input d,enable,reset,clk,output reg q);

    always @(posedge clk, posedge reset) begin  //reset asincrono
        if (reset) q = 0; // si el reset esta activado la salida se coloca en 0
        else if (enable) q = d; //si reset esta en 0 y ademas esta enable en 1, entonces deja pasar d a q
    end

endmodule

module FlipFlopD2b(input wire [1:0] d, input wire enable, reset, clk, output wire [1:0] q );

    FlipFlopD1b FF1(d[0], enable, reset,clk, q[0]);//primer FF
    FlipFlopD1b FF2(d[1], enable, reset,clk, q[1]);//segundo FF

endmodule

module FlipFlopD4b(input [3:0] d, input wire enable, reset, clk, output wire [3:0] q );

    FlipFlopD2b FF1(d[1:0], enable, reset,clk, q[1:0]); // FF de los bits 0 y 1
    FlipFlopD2b FF2(d[3:2], enable, reset,clk, q[3:2]); // Ff de los bits 2 y 3

endmodule

Laboratorio09/Ejercicio01/flipflop_tb.v
module testbench();

    reg [3:0] d;
    reg [1:0] d1;
    reg d2;
    reg enable,reset,clk;
    wire [3:0]  q; 
    wire [1:0] q1;
    wire q2;

    FlipFlopD4b FF(d,enable,reset,clk,q);
    FlipFlopD2b ff1(d1,enable,reset,clk,q1);
    FlipFlopD1b ff2(d2,enable,reset,clk,q2);
    initial clk = 0;

    always #1 clk = ~clk;


    initial begin
        
        reset = 0; enable = 0; d = 0;
        #1 reset = 1;
        #2 reset = 0;
        #2 enable = 1;
        #3  d = 4'b0101;
        #2 enable = 0;
        #2 d = 3;
        #2 d= 12;
        #4 enable = 1;
        //FF de 2 bits
        #2 d1 = 2;
        #4 enable = 0;
        #2  d1=1;
        #2  reset = 1;
        #2  reset= 0;
        #2  d1 = 3;
        #2  enable = 1;
        //FF de 1 bit
        #2  enable = 0;
        #1 reset =1;
        #1  reset = 0;
        #2  d2 = 1;
        #2  enable = 1;
        #4  d2 = 0;

        #5 $finish; 


    end

initial begin
        $dumpfile("flipflop_tb.vcd");
        $dumpvars(0,testbench);
    end

endmodule

Laboratorio09/Ejercicio01/flipflop_tb.vcd
$date
	Sat Oct 31 00:06:44 2020
$end
$version
	Icarus Verilog
$end
$timescale
	1ps
$end
$scope module testbench $end
$var wire 1 ! q2 $end
$var wire 2 " q1 [1:0] $end
$var wire 4 # q [3:0] $end
$var reg 1 $ clk $end
$var reg 4 % d [3:0] $end
$var reg 2 & d1 [1:0] $end
$var reg 1 ' d2 $end
$var reg 1 ( enable $end
$var reg 1 ) reset $end
$scope module FF $end
$var wire 1 $ clk $end
$var wire 4 * d [3:0] $end
$var wire 1 ( enable $end
$var wire 1 ) reset $end
$var wire 4 + q [3:0] $end
$scope module FF1 $end
$var wire 1 $ clk $end
$var wire 2 , d [1:0] $end
$var wire 1 ( enable $end
$var wire 1 ) reset $end
$var wire 2 - q [1:0] $end
$scope module FF1 $end
$var wire 1 $ clk $end
$var wire 1 . d $end
$var wire 1 ( enable $end
$var wire 1 ) reset $end
$var reg 1 / q $end
$upscope $end
$scope module FF2 $end
$var wire 1 $ clk $end
$var wire 1 0 d $end
$var wire 1 ( enable $end
$var wire 1 ) reset $end
$var reg 1 1 q $end
$upscope $end
$upscope $end
$scope module FF2 $end
$var wire 1 $ clk $end
$var wire 2 2 d [1:0] $end
$var wire 1 ( enable $end
$var wire 1 ) reset $end
$var wire 2 3 q [1:0] $end
$scope module FF1 $end
$var wire 1 $ clk $end
$var wire 1 4 d $end
$var wire 1 ( enable $end
$var wire 1 ) reset $end
$var reg 1 5 q $end
$upscope $end
$scope module FF2 $end
$var wire 1 $ clk $end
$var wire 1 6 d $end
$var wire 1 ( enable $end
$var wire 1 ) reset $end
$var reg 1 7 q $end
$upscope $end
$upscope $end
$upscope $end
$scope module ff1 $end
$var wire 1 $ clk $end
$var wire 2 8 d [1:0] $end
$var wire 1 ( enable $end
$var wire 1 ) reset $end
$var wire 2 9 q [1:0] $end
$scope module FF1 $end
$var wire 1 $ clk $end
$var wire 1 : d $end
$var wire 1 ( enable $end
$var wire 1 ) reset $end
$var reg 1 ; q $end
$upscope $end
$scope module FF2 $end
$var wire 1 $ clk $end
$var wire 1 < d $end
$var wire 1 ( enable $end
$var wire 1 ) reset $end
$var reg 1 = q $end
$upscope $end
$upscope $end
$scope module ff2 $end
$var wire 1 $ clk $end
$var wire 1 ' d $end
$var wire 1 ( enable $end
$var wire 1 ) reset $end
$var reg 1 ! q $end
$upscope $end
$upscope $end
$enddefinitions $end
#0
$dumpvars
x=
x<
x;
x:
bx 9
bx 8
x7
06
x5
04
bx 3
b0 2
x1
00
x/
0.
bx -
b0 ,
bx +
b0 *
0)
0(
x'
bx &
b0 %
0$
bx #
bx "
x!
$end
#1
0/
b0 -
01
05
b0 #
b0 +
b0 3
07
0;
b0 "
b0 9
0=
0!
1)
1$
#2
0$
#3
1$
0)
#4
0$
#5
x;
bx "
bx 9
x=
x!
1$
1(
#6
0$
#7
1$
#8
1.
14
b1 ,
b1 2
0$
b101 %
b101 *
#9
b1 -
1/
b101 #
b101 +
b1 3
15
1$
#10
0$
0(
#11
1$
#12
10
04
b11 ,
b0 2
0$
b11 %
b11 *
#13
1$
#14
0.
00
14
16
b0 ,
b11 2
0$
b1100 %
b1100 *
#15
1$
#16
0$
#17
1$
#18
0$
1(
#19
b11 3
17
b1100 #
b1100 +
b0 -
0/
1$
#20
0:
1<
0$
b10 &
b10 8
#21
0;
b10 "
b10 9
1=
1$
#22
0$
#23
1$
#24
0$
0(
#25
1$
#26
1:
0<
0$
b1 &
b1 8
#27
1$
#28
05
b0 #
b0 +
b0 3
07
b0 "
b0 9
0=
0!
0$
1)
#29
1$
#30
0$
0)
#31
1$
#32
1<
0$
b11 &
b11 8
#33
1$
#34
0$
1(
#35
15
b1100 #
b1100 +
b11 3
17
1;
b11 "
b11 9
1=
x!
1$
#36
0$
0(
#37
0!
0=
b0 "
b0 9
0;
07
b0 #
b0 +
b0 3
05
1$
1)
#38
0$
0)
#39
1$
#40
0$
1'
#41
1$
#42
0$
1(
#43
15
b1100 #
b1100 +
b11 3
17
1;
b11 "
b11 9
1=
1!
1$
#44
0$
#45
1$
#46
0$
0'
#47
0!
1$
