Laboratorio06/Ejercicio06/ejercicio06.v
//ejercicio 1
module maquinaMealy(input A,B,clk,reset, output y);
    reg [1:0]estado;
    wire [1:0]estado_siguiente;
    wire nodo1;

    assign nodo1 = estado[1] & A & B ; //nodo que sirve tanto para la salida como para el bit s1 del estado
    assign estado_siguiente[0]= ~estado[1] & ~estado[0] & A; //S0 del siguente estado
    assign estado_siguiente[1]=  nodo1 | (estado[0] & B);//S1 del siguiente estado
    assign y = nodo1; 

    // se asigna 00 al estado si reset esta en 1, de forma asincrona, si es 0, la maquina sigue su ejecucion normal
    // se mueve a estado el estado siguente en cada flanco positivo de reloj (no blocking).
    always @ (posedge clk, posedge reset) estado <= reset? 2'b00 : estado_siguiente;

endmodule

// ejercicio 03
module contadorGray(input upNotDown, clk, reset, output wire [2:0]salida );
    reg [2:0] estado;
    wire [2:0] estado_siguiente;
    //Nodos auxiliares
    wire n1,n2,n3;
    wire n4,n5,n6;
    wire n7,n8,n9,n10;
    // implementacion de las ecuaciones obtenidas con Logic Friday
    assign   n1= ~estado[1] & ~estado[0] & ~upNotDown;
    assign   n2= estado[1] &  ~estado[0] & upNotDown;
    assign   n3= estado[2] & estado[0];

    assign    n4= ~estado[2] & estado[0] & upNotDown;
    assign    n5= estado[2] & estado[0] & ~upNotDown;
    assign    n6 = estado[1] & ~estado[0];

    assign    n7 = ~estado[2] & ~estado[1] & upNotDown;
    assign    n8 = estado[2] & ~estado[1] & ~upNotDown;
    assign    n9 = ~estado[2] & estado[1] & ~upNotDown;
    assign    n10 = estado[2] & estado[1] & upNotDown;

    assign estado_siguiente = {n1 | n2 | n3, n4 | n5 | n6, n7| n8 | n9 |n10 };
    // se eligio la codificacion de los estados de forma que coincidieran con los valores de salida solicitados
    assign salida = estado;
       

    always @(posedge clk , posedge reset) estado <= reset ? 3'b000 : estado_siguiente; 

endmodule

Laboratorio06/Ejercicio06/ejercicio06_tb.v
module testbench();
    //----- Variables para el ejercicio 01--------------
    reg A,B;
    reg reset01;
    wire out01;
    //------ Variables para el ejercicio 03------------
    reg upNotDown;
    reg reset03;
    wire [2:0]out03;
    //---- reloj ---------
    reg clk;

    maquinaMealy Ejercicio01(A,B,clk,reset01,out01);
    contadorGray contador(upNotDown,clk,reset03,out03);

    initial clk =0 ; //se inicializa el reloj

    initial begin// ejercicio 01 ver timing
        reset01=0;
        #1 reset01=1;
        #1 reset01=0; // se inicia la operacion de la FSM
        #1 A=0; B=0;
        #17 B=1;
        #20 A=1;B=0;
        #100 B=1;
        #20  B=0;
        #40  B=1;
        #20  A=0; B=0;
        #20 $finish;
    end

    initial begin
        reset03=0; upNotDown = 1;
        #1 reset03=1;
        #1 reset03=0;
        #138 upNotDown=0;
    end

    always #10 clk= ~clk ;//onda cuadrada con periodo de 20 ciclos

    initial begin
        $dumpfile("ejercicio06_tb.vcd");
        $dumpvars(0,testbench);
    end

endmodule

Laboratorio06/Ejercicio06/ejercicio06_tb.vcd
$date
	Sat Sep 05 15:13:05 2020
$end
$version
	Icarus Verilog
$end
$timescale
	1ps
$end
$scope module testbench $end
$var wire 3 ! out03 [2:0] $end
$var wire 1 " out01 $end
$var reg 1 # A $end
$var reg 1 $ B $end
$var reg 1 % clk $end
$var reg 1 & reset01 $end
$var reg 1 ' reset03 $end
$var reg 1 ( upNotDown $end
$scope module Ejercicio01 $end
$var wire 1 # A $end
$var wire 1 $ B $end
$var wire 1 % clk $end
$var wire 1 ) nodo1 $end
$var wire 1 & reset $end
$var wire 1 " y $end
$var wire 2 * estado_siguiente [1:0] $end
$var reg 2 + estado [1:0] $end
$upscope $end
$scope module contador $end
$var wire 1 % clk $end
$var wire 1 , n1 $end
$var wire 1 - n10 $end
$var wire 1 . n2 $end
$var wire 1 / n3 $end
$var wire 1 0 n4 $end
$var wire 1 1 n5 $end
$var wire 1 2 n6 $end
$var wire 1 3 n7 $end
$var wire 1 4 n8 $end
$var wire 1 5 n9 $end
$var wire 1 ' reset $end
$var wire 3 6 salida [2:0] $end
$var wire 1 ( upNotDown $end
$var wire 3 7 estado_siguiente [2:0] $end
$var reg 3 8 estado [2:0] $end
$upscope $end
$upscope $end
$enddefinitions $end
#0
$dumpvars
bx 8
bx 7
bx 6
05
04
x3
x2
01
x0
x/
x.
x-
0,
bx +
bx *
x)
1(
0'
0&
0%
x$
x#
x"
bx !
$end
#1
b1 7
13
b0x *
0.
00
0-
0"
0)
0/
02
b0 !
b0 6
b0 8
b0 +
1'
1&
#2
0'
0&
#3
b0 *
0$
0#
#10
b11 7
10
b1 !
b1 6
b1 8
1%
#20
0%
1$
#30
b10 7
03
b11 !
b11 6
b11 8
1%
#40
b1 *
0%
0$
1#
#50
b110 7
b0 *
1.
00
12
b1 +
b10 !
b10 6
b10 8
1%
#60
0%
#70
b1 *
b111 7
1-
b0 +
b110 !
b110 6
b110 8
1%
#80
0%
#90
b0 *
0.
b101 7
02
1/
b1 +
b111 !
b111 6
b111 8
1%
#100
0%
#110
b1 *
b100 7
0-
b0 +
b101 !
b101 6
b101 8
1%
#120
0%
#130
b0 *
b0 7
0/
b1 +
b100 !
b100 6
b100 8
1%
#140
b101 7
b10 *
1,
14
0%
1$
0(
#150
b111 7
0,
1"
1)
b10 *
11
1/
b10 +
b101 !
b101 6
b101 8
1%
#160
b0 *
0"
0)
0%
0$
#170
b110 7
b1 *
04
b0 +
b111 !
b111 6
b111 8
1%
#180
0%
#190
b0 *
b10 7
01
12
0/
b1 +
b110 !
b110 6
b110 8
1%
#200
b10 *
0%
1$
#210
b11 7
15
1"
1)
b10 *
b10 +
b10 !
b10 6
b10 8
1%
#220
b0 *
0"
0)
0%
0$
0#
#230
b1 7
02
b0 +
b11 !
b11 6
b11 8
1%
