Laboratorio05/Ejercicio04.v
module Mux2_1(input wire D0,D1,S0, output wire out);
    assign out = S0 ? D1 : D0 ;
endmodule

module Mux4_1(input wire D0,D1,D2,D3,S1,S0,output wire out);
    wire out1,out2; 
    Mux2_1 m1(D0,D1,S0,out1);
    Mux2_1 m2(D2,D3,S0,out2);

    Mux2_1 m3(out1,out2,S1,out);
endmodule

module Mux8_1(input wire D0,D1,D2,D3,D4,D5,D6,D7,S2,S1,S0,output wire out);
    wire out4_1,out4_2;

    Mux4_1 m1(D0,D1,D2,D3,S1,S0,out4_1);
    Mux4_1 m2(D4,D5,D6,D7,S1,S0,out4_2);
    Mux2_1 m3(out4_1,out4_2,S2,out);

endmodule

module Tabla1Mux8_1(input wire a,b,c, output wire out);
    Mux8_1  m1(1'b0,1'b1,1'b1,1'b0,1'b1,1'b0,1'b0,1'b1,a,b,c,out);
endmodule

module Tabla1Mux4_1(input wire a,b,c,output wire out);
    wire notC;
    assign notC = ~c;

    Mux4_1 m1(c,notC,notC,c,a,b,out);
endmodule

module Tabla1Mux2_1(input wire a,b,c, output wire out);
    wire xorBC,xnorBC;
    assign xorBC = b * ~c + ~b * c ;
    assign xnorBC = ~xorBC;

    Mux2_1 m1(xorBC,xnorBC,a,out);
endmodule

module Tabla2Mux8_1 (input wire a,b,c, output wire out);

    Mux8_1 m1(1'b1,1'b0,1'b0,1'b0,1'b0,1'b1,1'b1,1'b0,a,b,c,out);

endmodule

module Tabla2Mux4_1 (input wire a,b,c,output wire out);
    wire notC;
    assign notC = ~c;
    Mux4_1  m1(1'b1,1'b0,1'b1,notC,a,b,out);
endmodule

module Tabla2Mux2_1 (input wire a,b,c, output wire out);
    wire norBC, xorBC;
    assign norBC = ~(b | c);
    assign xorBC = b & ~c  |  ~b &c ;

    Mux2_1 m1(norBC,xorBC,a,out);
endmodule

Laboratorio05/Ejercicio04_tb.v
module testbench();
    reg a,b,c;
    reg a1,b1,c1;
    wire out1,out2,out3,out4,out5,out6;

Tabla1Mux8_1 t1(a,b,c,out1);
Tabla1Mux4_1 t2(a,b,c,out2);
Tabla1Mux2_1 t3(a,b,c,out3);

Tabla2Mux8_1 t4(a1,b1,c1,out4);
Tabla2Mux4_1 t5(a1,b1,c1,out5);
Tabla2Mux2_1 t6(a1,b1,c1,out6);

initial begin  //mostrar tablas de verdad
    $display("-----------------Tabla 1-------------------------");
    $display("|      Mux 8:1       Mux 4:1        Mux 2:1 ");
    $display("|    ----------    ----------     -----------");
    $display("|    A B C | Y     A B C | Y       A B C | Y  ");
    $monitor("|    %b %b %b | %b     %b %b %b | %b       %b %b %b | %b",a,b,c,out1,a,b,c,out2,a,b,c,out3);
    #7
    $display("-----------------Tabla 2-------------------------");
    $display("|      Mux 8:1       Mux 4:1        Mux 2:1 ");
    $display("|    ----------    ----------     -----------");
    $display("|    A B C | Y     A B C | Y       A B C | Y  ");
    $monitor("|    %b %b %b | %b     %b %b %b | %b       %b %b %b | %b",a1,b1,c1,out4,a1,b1,c1,out5,a1,b1,c1,out6);
    
end

initial begin
    a=0; b=0; c=0;
    #1 c=1;
    #1 b=1; c=0;
    #1 c=1;
    #1 a=1; b=0; c=0;
    #1 c=1;
    #1 b=1; c=0;
    #1 c=1;
end

initial begin
    #7 
    a1=0; b1=0; c1=0;
    #1 c1=1;
    #1 b1=1; c1=0;
    #1 c1=1;
    #1 a1=1; b1=0; c1=0;
    #1 c1=1;
    #1 b1=1; c1=0;
    #1 c1=1;
end

initial #15 $finish;
    initial begin
        $dumpfile("Ejercicio04_tb.vcd");
        $dumpvars(0,testbench);
    end
endmodule

Laboratorio05/Ejercicio04_tb.vcd
$date
	Sat Aug 15 14:54:10 2020
$end
$version
	Icarus Verilog
$end
$timescale
	1ps
$end
$scope module testbench $end
$var wire 1 ! out6 $end
$var wire 1 " out5 $end
$var wire 1 # out4 $end
$var wire 1 $ out3 $end
$var wire 1 % out2 $end
$var wire 1 & out1 $end
$var reg 1 ' a $end
$var reg 1 ( a1 $end
$var reg 1 ) b $end
$var reg 1 * b1 $end
$var reg 1 + c $end
$var reg 1 , c1 $end
$scope module t1 $end
$var wire 1 ' a $end
$var wire 1 ) b $end
$var wire 1 + c $end
$var wire 1 & out $end
$scope module m1 $end
$var wire 1 - D0 $end
$var wire 1 . D1 $end
$var wire 1 / D2 $end
$var wire 1 0 D3 $end
$var wire 1 1 D4 $end
$var wire 1 2 D5 $end
$var wire 1 3 D6 $end
$var wire 1 4 D7 $end
$var wire 1 + S0 $end
$var wire 1 ) S1 $end
$var wire 1 ' S2 $end
$var wire 1 5 out4_2 $end
$var wire 1 6 out4_1 $end
$var wire 1 & out $end
$scope module m1 $end
$var wire 1 - D0 $end
$var wire 1 . D1 $end
$var wire 1 / D2 $end
$var wire 1 0 D3 $end
$var wire 1 + S0 $end
$var wire 1 ) S1 $end
$var wire 1 7 out2 $end
$var wire 1 8 out1 $end
$var wire 1 6 out $end
$scope module m1 $end
$var wire 1 - D0 $end
$var wire 1 . D1 $end
$var wire 1 + S0 $end
$var wire 1 8 out $end
$upscope $end
$scope module m2 $end
$var wire 1 / D0 $end
$var wire 1 0 D1 $end
$var wire 1 + S0 $end
$var wire 1 7 out $end
$upscope $end
$scope module m3 $end
$var wire 1 8 D0 $end
$var wire 1 7 D1 $end
$var wire 1 ) S0 $end
$var wire 1 6 out $end
$upscope $end
$upscope $end
$scope module m2 $end
$var wire 1 1 D0 $end
$var wire 1 2 D1 $end
$var wire 1 3 D2 $end
$var wire 1 4 D3 $end
$var wire 1 + S0 $end
$var wire 1 ) S1 $end
$var wire 1 9 out2 $end
$var wire 1 : out1 $end
$var wire 1 5 out $end
$scope module m1 $end
$var wire 1 1 D0 $end
$var wire 1 2 D1 $end
$var wire 1 + S0 $end
$var wire 1 : out $end
$upscope $end
$scope module m2 $end
$var wire 1 3 D0 $end
$var wire 1 4 D1 $end
$var wire 1 + S0 $end
$var wire 1 9 out $end
$upscope $end
$scope module m3 $end
$var wire 1 : D0 $end
$var wire 1 9 D1 $end
$var wire 1 ) S0 $end
$var wire 1 5 out $end
$upscope $end
$upscope $end
$scope module m3 $end
$var wire 1 6 D0 $end
$var wire 1 5 D1 $end
$var wire 1 ' S0 $end
$var wire 1 & out $end
$upscope $end
$upscope $end
$upscope $end
$scope module t2 $end
$var wire 1 ' a $end
$var wire 1 ) b $end
$var wire 1 + c $end
$var wire 1 ; notC $end
$var wire 1 % out $end
$scope module m1 $end
$var wire 1 + D0 $end
$var wire 1 ; D1 $end
$var wire 1 ; D2 $end
$var wire 1 + D3 $end
$var wire 1 ) S0 $end
$var wire 1 ' S1 $end
$var wire 1 < out2 $end
$var wire 1 = out1 $end
$var wire 1 % out $end
$scope module m1 $end
$var wire 1 + D0 $end
$var wire 1 ; D1 $end
$var wire 1 ) S0 $end
$var wire 1 = out $end
$upscope $end
$scope module m2 $end
$var wire 1 ; D0 $end
$var wire 1 + D1 $end
$var wire 1 ) S0 $end
$var wire 1 < out $end
$upscope $end
$scope module m3 $end
$var wire 1 = D0 $end
$var wire 1 < D1 $end
$var wire 1 ' S0 $end
$var wire 1 % out $end
$upscope $end
$upscope $end
$upscope $end
$scope module t3 $end
$var wire 1 ' a $end
$var wire 1 ) b $end
$var wire 1 + c $end
$var wire 1 > xnorBC $end
$var wire 1 ? xorBC $end
$var wire 1 $ out $end
$scope module m1 $end
$var wire 1 ? D0 $end
$var wire 1 > D1 $end
$var wire 1 ' S0 $end
$var wire 1 $ out $end
$upscope $end
$upscope $end
$scope module t4 $end
$var wire 1 ( a $end
$var wire 1 * b $end
$var wire 1 , c $end
$var wire 1 # out $end
$scope module m1 $end
$var wire 1 @ D0 $end
$var wire 1 A D1 $end
$var wire 1 B D2 $end
$var wire 1 C D3 $end
$var wire 1 D D4 $end
$var wire 1 E D5 $end
$var wire 1 F D6 $end
$var wire 1 G D7 $end
$var wire 1 , S0 $end
$var wire 1 * S1 $end
$var wire 1 ( S2 $end
$var wire 1 H out4_2 $end
$var wire 1 I out4_1 $end
$var wire 1 # out $end
$scope module m1 $end
$var wire 1 @ D0 $end
$var wire 1 A D1 $end
$var wire 1 B D2 $end
$var wire 1 C D3 $end
$var wire 1 , S0 $end
$var wire 1 * S1 $end
$var wire 1 J out2 $end
$var wire 1 K out1 $end
$var wire 1 I out $end
$scope module m1 $end
$var wire 1 @ D0 $end
$var wire 1 A D1 $end
$var wire 1 , S0 $end
$var wire 1 K out $end
$upscope $end
$scope module m2 $end
$var wire 1 B D0 $end
$var wire 1 C D1 $end
$var wire 1 , S0 $end
$var wire 1 J out $end
$upscope $end
$scope module m3 $end
$var wire 1 K D0 $end
$var wire 1 J D1 $end
$var wire 1 * S0 $end
$var wire 1 I out $end
$upscope $end
$upscope $end
$scope module m2 $end
$var wire 1 D D0 $end
$var wire 1 E D1 $end
$var wire 1 F D2 $end
$var wire 1 G D3 $end
$var wire 1 , S0 $end
$var wire 1 * S1 $end
$var wire 1 L out2 $end
$var wire 1 M out1 $end
$var wire 1 H out $end
$scope module m1 $end
$var wire 1 D D0 $end
$var wire 1 E D1 $end
$var wire 1 , S0 $end
$var wire 1 M out $end
$upscope $end
$scope module m2 $end
$var wire 1 F D0 $end
$var wire 1 G D1 $end
$var wire 1 , S0 $end
$var wire 1 L out $end
$upscope $end
$scope module m3 $end
$var wire 1 M D0 $end
$var wire 1 L D1 $end
$var wire 1 * S0 $end
$var wire 1 H out $end
$upscope $end
$upscope $end
$scope module m3 $end
$var wire 1 I D0 $end
$var wire 1 H D1 $end
$var wire 1 ( S0 $end
$var wire 1 # out $end
$upscope $end
$upscope $end
$upscope $end
$scope module t5 $end
$var wire 1 ( a $end
$var wire 1 * b $end
$var wire 1 , c $end
$var wire 1 N notC $end
$var wire 1 " out $end
$scope module m1 $end
$var wire 1 O D0 $end
$var wire 1 P D1 $end
$var wire 1 Q D2 $end
$var wire 1 N D3 $end
$var wire 1 * S0 $end
$var wire 1 ( S1 $end
$var wire 1 R out2 $end
$var wire 1 S out1 $end
$var wire 1 " out $end
$scope module m1 $end
$var wire 1 O D0 $end
$var wire 1 P D1 $end
$var wire 1 * S0 $end
$var wire 1 S out $end
$upscope $end
$scope module m2 $end
$var wire 1 Q D0 $end
$var wire 1 N D1 $end
$var wire 1 * S0 $end
$var wire 1 R out $end
$upscope $end
$scope module m3 $end
$var wire 1 S D0 $end
$var wire 1 R D1 $end
$var wire 1 ( S0 $end
$var wire 1 " out $end
$upscope $end
$upscope $end
$upscope $end
$scope module t6 $end
$var wire 1 ( a $end
$var wire 1 * b $end
$var wire 1 , c $end
$var wire 1 T norBC $end
$var wire 1 U xorBC $end
$var wire 1 ! out $end
$scope module m1 $end
$var wire 1 T D0 $end
$var wire 1 U D1 $end
$var wire 1 ( S0 $end
$var wire 1 ! out $end
$upscope $end
$upscope $end
$upscope $end
$enddefinitions $end
#0
$dumpvars
xU
xT
xS
xR
1Q
0P
1O
xN
xM
xL
xK
0J
xI
xH
0G
1F
1E
0D
0C
0B
0A
1@
0?
1>
0=
1<
1;
1:
09
08
17
06
15
14
03
02
11
00
1/
1.
0-
x,
0+
x*
0)
x(
0'
0&
0%
0$
x#
x"
x!
$end
#1
1&
16
05
0<
1%
18
07
0:
19
0;
1=
1$
0>
1?
1+
#2
1&
1%
08
17
1:
09
1;
1$
0>
16
05
1=
1?
0+
1)
#3
0&
0%
06
15
0=
0$
1>
18
07
0:
19
0;
1<
0?
1+
#4
08
17
1:
09
1;
06
15
1<
1&
1%
1$
0+
0)
1'
#5
0&
0%
16
05
0<
0$
18
07
0:
19
0;
1=
0>
1?
1+
#6
0$
0&
08
17
1:
09
1;
0>
16
05
1=
1?
0+
1)
#7
1&
1$
1#
1!
06
15
0=
1%
1>
1I
0H
1"
1T
0U
18
07
0:
19
0;
1<
0?
1K
0M
1L
1N
1S
1R
1+
0,
0*
0(
#8
0#
0!
0I
1H
0T
1U
0K
1M
0L
0N
1,
#9
1U
0"
1K
0M
1L
1N
1H
0S
1R
0,
1*
#10
0U
0H
0R
0K
1M
0L
0N
1,
#11
1I
0#
1"
1T
1K
0M
1L
1N
0H
1S
1R
0,
0*
1(
#12
1#
1!
0I
1H
0T
1U
0K
1M
0L
0N
1,
#13
1!
1U
1#
1"
1K
0M
1L
1N
1H
0S
1R
0,
1*
#14
0!
0#
0"
0U
0H
0R
0K
1M
0L
0N
1,
