Laboratorio04/Ejercicio5/alarma.v
module AlarmaPOS(input wire sistema, ventana, movimiento, output wire alarma);
    wire w1,w2,w3;
    assign w1 = sistema & ~ventana & movimiento;
    assign w2 = sistema & ~ventana & ~movimiento;
    assign w3 = sistema & ventana  & movimiento;
    assign alarma  = w1 |  w2 | w3 ;
endmodule

module AlarmaSOP(input wire sistema, ventana,movimiento, output wire alarma);
    wire notS,notV,notM;
    wire w1,w2,w3,w4,w5;
    //negaciones
    not N1(notS, sistema);
    not N2(notV, ventana);
    not N3(notM, movimiento);
    //sumas
    or O1(w1,sistema,ventana,movimiento);
    or O2(w2,sistema,ventana,notM);
    or O3(w3,sistema,notV, movimiento);
    or O4(w4,sistema,notV,notM);
    or O5(w5,notS,notV,movimiento);
    //multiplicacion
    and A1(alarma, w1,w2,w3,w4,w5);
endmodule

module AlarmaKarnaught(input wire sistema, ventana,movimiento, output wire alarma);
    assign alarma = (sistema & movimiento) | (sistema & ~ventana);
endmodule

Laboratorio04/Ejercicio5/alarma_tb.v
module testbench();
    reg sistema,ventana,movimiento;
    wire alarma1;
    wire alarma2;
    wire alarma3;

    AlarmaPOS  A1(sistema,ventana,movimiento,alarma1);
    AlarmaSOP  A2(sistema,ventana,movimiento,alarma2);
    AlarmaKarnaught A3(sistema,ventana,movimiento,alarma3);

    initial begin
        #2
        $display("---------------------Sistema de alarma----------------------------");
        $display("| Sistema ventana/puerta  Sensor movimiento  |  POS   SOP  Reducida");
        $display("| ------- --------------  -----------------  |  ---   ---  --------");
        $monitor("|   %b         %b              %b               |   %b    %b    %b ",sistema,ventana,movimiento,
        alarma1,alarma2, alarma3);
        sistema= 0; ventana=0; movimiento=0;
        #1 movimiento=1;
        #1 ventana=1; movimiento=0;
        #1 movimiento=1;
        #1 sistema= 1; ventana=0; movimiento=0;
        #1 movimiento=1;
        #1 ventana=1; movimiento=0;
        #1 movimiento=1;
        #1 $finish;
    end

    initial begin
        $dumpfile("alarma_tb.vcd");
        $dumpvars(0,testbench);
    end
endmodule

Laboratorio04/Ejercicio5/alarma_tb.vcd
$date
	Sun Aug 09 13:58:06 2020
$end
$version
	Icarus Verilog
$end
$timescale
	1ps
$end
$scope module testbench $end
$var wire 1 ! alarma3 $end
$var wire 1 " alarma2 $end
$var wire 1 # alarma1 $end
$var reg 1 $ movimiento $end
$var reg 1 % sistema $end
$var reg 1 & ventana $end
$scope module A1 $end
$var wire 1 # alarma $end
$var wire 1 $ movimiento $end
$var wire 1 % sistema $end
$var wire 1 & ventana $end
$var wire 1 ' w1 $end
$var wire 1 ( w2 $end
$var wire 1 ) w3 $end
$upscope $end
$scope module A2 $end
$var wire 1 " alarma $end
$var wire 1 $ movimiento $end
$var wire 1 * notM $end
$var wire 1 + notS $end
$var wire 1 , notV $end
$var wire 1 % sistema $end
$var wire 1 & ventana $end
$var wire 1 - w1 $end
$var wire 1 . w2 $end
$var wire 1 / w3 $end
$var wire 1 0 w4 $end
$var wire 1 1 w5 $end
$upscope $end
$scope module A3 $end
$var wire 1 ! alarma $end
$var wire 1 $ movimiento $end
$var wire 1 % sistema $end
$var wire 1 & ventana $end
$upscope $end
$upscope $end
$enddefinitions $end
#0
$dumpvars
x1
x0
x/
x.
x-
x,
x+
x*
x)
x(
x'
x&
x%
x$
x#
x"
x!
$end
#2
0#
0"
1.
1/
10
0(
0!
0'
0)
1*
11
1,
1+
0-
0$
0&
0%
#3
0"
0.
0*
1-
1$
#4
1*
0/
0,
1.
0$
1&
#5
0"
00
0*
1/
1$
#6
1#
1!
1"
1(
1*
1,
0+
10
0$
0&
1%
#7
0(
1'
0*
1$
#8
0#
0"
0!
0'
1*
01
0,
0$
1&
#9
1"
1#
1!
1)
0*
11
1$
