Laboratorio06/Ejercicio05/ejercicio05.v
module flip_flopD(input wire [3:0]d,input wire clk, input wire reset, set, output reg [3:0] Q);
    

    /* se le asigna a la salida los sigientes valores, durante el flanco de subida
        d si set y reset se encuentran ambos en 0
        1111 si set esta en 1 sin importar lo que se encuentre en 
    */
    always @ (posedge clk) Q <= ( reset ? 4'b0000 : d) | (set ? 4'b1111 : 4'b0000) ;  
    always @ (posedge reset) Q = 4'b0000;
endmodule

Laboratorio06/Ejercicio05/ejercicio05_tb.v
module testbench();
    reg  [3:0] d; //entrada al flip flop
    wire [3:0] out; //salida 
    reg clk,rst,set;// reloj y reset

    flip_flopD fp(d,clk,rst,set,out);
    initial begin
        d = 4'b0000; rst= 0; set=0;
        #1
        d=4'b0001;
        #2
        d=4'b0010;  
        #4   
        d=4'b0100;
        #4
        d=4'b1000;
        #1
        rst =1;
        #1
        d=4'b0001;
        #2
        d=4'b0010;  
        #4   
        d=4'b0100;
        #4
        d=4'b1000;
        #1
        d = 4'b0000; rst= 0; set=0;
        #1
        d=4'b0001;
        #2
        d=4'b0010;  
        #4   
        d=4'b0100;
        #4
        d=4'b1000;
        d = 4'b0000; rst= 0; set=1;
        #3
        d=4'b0010;  
        #4   
        d=4'b0100;
        #1
        rst =1;
        #1
        d=4'b0001;
        #2
        d=4'b0010;  



    end
    initial begin
        clk = 0;
        #2 clk = 1;
        #2 clk = 0;
        #2 clk = 1;
        #2 clk = 0;
        #2 clk = 1;
        #2 clk = 0;
        #2 clk = 1;
        #2 clk = 0;
        #2 clk = 1;
        #2 clk = 0;
        #2 clk = 1;
        #2 clk = 0;
        #2 clk = 1;
        #2 clk = 0;
        #2 clk = 1;
        #2 clk = 0;
        #2 clk = 1;
        #2 clk = 0;
        #2 clk = 1;
        #2 clk = 0;
        #2 clk = 1;
        #2 clk = 0;
        #2 clk = 1;
        #2 clk = 0;
        #2 clk = 1;
        #2 clk = 0;
        #1 $finish;
    end
    initial begin
        $dumpfile("ejercicio05_tb.vcd");
        $dumpvars(0,testbench);
    end
endmodule

Laboratorio06/Ejercicio05/ejercicio05_tb.vcd
$date
	Sat Sep 05 03:49:14 2020
$end
$version
	Icarus Verilog
$end
$timescale
	1ps
$end
$scope module testbench $end
$var wire 4 ! out [3:0] $end
$var reg 1 " clk $end
$var reg 4 # d [3:0] $end
$var reg 1 $ rst $end
$var reg 1 % set $end
$scope module fp $end
$var wire 1 " clk $end
$var wire 4 & d [3:0] $end
$var wire 1 $ reset $end
$var wire 1 % set $end
$var reg 4 ' Q [3:0] $end
$upscope $end
$upscope $end
$enddefinitions $end
#0
$dumpvars
bx '
b0 &
0%
0$
b0 #
0"
bx !
$end
#1
b1 #
b1 &
#2
b1 !
b1 '
1"
#3
b10 #
b10 &
#4
0"
#6
b10 !
b10 '
1"
#7
b100 #
b100 &
#8
0"
#10
b100 !
b100 '
1"
#11
b1000 #
b1000 &
#12
b0 !
b0 '
1$
0"
#13
b1 #
b1 &
#14
1"
#15
b10 #
b10 &
#16
0"
#18
1"
#19
b100 #
b100 &
#20
0"
#22
1"
#23
b1000 #
b1000 &
#24
0$
b0 #
b0 &
0"
#25
b1 #
b1 &
#26
b1 !
b1 '
1"
#27
b10 #
b10 &
#28
0"
#30
b10 !
b10 '
1"
#31
b100 #
b100 &
#32
0"
#34
b100 !
b100 '
1"
#35
1%
b0 #
b0 &
#36
0"
#38
b1111 !
b1111 '
1"
b10 #
b10 &
#40
0"
#42
1"
b100 #
b100 &
#43
b0 !
b0 '
1$
#44
b1 #
b1 &
0"
#46
b1111 !
b1111 '
b10 #
b10 &
1"
