Laboratorio04/Ejercicio4/modulos.v
//ejercicio 1.1
module Ejercicio1Tabla1 (input wire a,b,c, output wire y);
    //structural
    wire notA,notB,notC;
    wire w1,w2,w3;
    // negaciones
    not N1(notA,a);
    not N2(notB,b);
    not N3(notC,c);
    // multiplicaciones
    and A1(w1,notA,notC);
    and A2(w2,a,notB);
    and A3(w3,a,c);
    // suma
    or O1(y,w1,w2,w3);
endmodule
//ejercicio 1.2
module Ejercicio1Tabla2(input wire a,b,c,output wire y);
    //structural
    not N1(y,b);
    
endmodule
//ejercicio 1.3
module Ejercicio1Tabla3(input wire a,b,c,d, output wire y);
    wire notA, notB,notC,notD;
    wire w1,w2,w3,w4,w5,w6,w7,w8;
    // structural
    //complemento
    not N1(notA,a);
    not N2(notB,b);
    not N3(notC,c);
    not N4(notD,d);
    //multiplicaciones
    and A1(w1,notA,notB,notC,notD);
    and A2(w2,a,b,notC,notD);
    and A3(w3,notA,b,notC,d);
    and A4(w4,a,notB,notC,d);
    and A5(w5,notA,notB,c,d);
    and A6(w6,a,b,c,d);
    and A7(w7,notA,b,c,notD);
    and A8(w8,a,notB,c,notD);
    // suma
    or O1(y,w1,w2,w3,w4,w5,w6,w7,w8);
endmodule
//ejercicio 1.4
module Ejercicio1Tabla4(input wire a,b,c,d, output wire y);
    wire notC,notD;

    wire w1,w2,w3;
    //complemento
    not N1(notC,c);
    not N2(notD,d);
    //multiplicaciones
    and A1(w1,a,c);
    and A2(w2,a,b);
    and A3(w3,a,notC,notD);
    // suma
    or O1(y,w1,w2,w3);
endmodule
//ejercicio 2.1
module  Ejercicio2Ecuacion1(input wire a,b,c,d,output wire y);
    wire w1,w2,w3,w4;
    assign w1 = a & ~c;
    assign w2 = a & ~b;
    assign w3 = a & ~d;
    assign w4 = ~b & ~c & ~d;
    assign y = w1 | w2 | w3 | w4 ;
endmodule
//ejercicio 2.2
module Ejercicio2Ecuacion2(input wire a,b,c, output wire y);
    assign y = ~b | c;
endmodule
//ejercicio 2.3 
module Ejercicio2Ecuacion3(input wire a,b,c,d, output wire y);
    wire w1,w2;
    assign w1 = ~c & d;
    assign w2 = a & d;
    assign y = b | w1 | w2;
endmodule

//ejercicio 2.4
module Ejercicio2Ecuacion4 (input wire a,b,c, output wire y);
    assign y= b | (~a & ~c);
endmodule

lab04/Ejercicio4/modulos_tb.v
module testbench();
//variables para ejercicio1tabla1
    reg a1_1, a1_2, a1_3;
    wire  y1_1;
//variables par ejercicio1tabla2
    reg a2_1, a2_2, a2_3;
    wire y1_2;
//variables par ejercicio1tabla3
    reg a3_1, a3_2, a3_3,a3_4;
    wire y1_3;
////variables par ejercicio1tabla4
    reg a4_1, a4_2, a4_3,a4_4;
    wire y1_4;
//variebles ejercicio2ecuacion1
    reg b1_1,b1_2,b1_3,b1_4;
    wire y2_1;
//variables ejericio3ecuacion2
    reg b2_1,b2_2,b2_3;
    wire y2_2;
//variebles ejercicio2ecuacion3
    reg b3_1,b3_2,b3_3,b3_4;
    wire y2_3;
    //variables ejericio3ecuacion2
    reg b4_1,b4_2,b4_3;
    wire y2_4;

    Ejercicio1Tabla1  Tabla1(a1_1,a1_2,a1_3,y1_1);
    Ejercicio1Tabla2  Tabla2(a2_1,a2_2,a2_3,y1_2);
    Ejercicio1Tabla3  Tabla3(a3_1,a3_2,a3_3,a3_4,y1_3);
    Ejercicio1Tabla4  Tabla4(a4_1,a4_2,a4_3,a4_4,y1_4);

    Ejercicio2Ecuacion1 Ecua1(b1_1,b1_2,b1_3,b1_4,y2_1);
    Ejercicio2Ecuacion2 Ecua2( b2_1,b2_2,b2_3,y2_2);
    Ejercicio2Ecuacion3 Ecua3(b3_1,b3_2,b3_3,b3_4,y2_3);
    Ejercicio2Ecuacion4 Ecua4( b4_1,b4_2,b4_3,y4_2);
    //encargado del display de los modulos del ejercicio 1
    initial begin
        $display("-------------------------Ejercicio 1-----------------------------");
        $display("| \t\t---Tabla 1---\t ---Tabla 2---  \t\t|");
        $display("| \t\t-------------\t -------------  \t\t|");
        $display("| \t\t  A B C | Y  \t   A B C | Y    \t\t|");
        $monitor("| \t\t  %b %b %b | %b  \t   %b %b %b | %b    \t\t|",a1_1, a1_2,a1_3, y1_1,a2_1,a2_2,a2_3,y1_2);
        #7
        $display("| \t\t---Tabla 3---\t ---Tabla 4---  \t\t|");
        $display("| \t\t-------------\t -------------  \t\t|");
        $display("| \t\t A B C D | Y\t  A B C D | Y    \t\t|");
        $monitor("| \t\t %b %b %b %b | %b \t  %b %b %b %b | %b    \t\t|",a3_1,a3_2,a3_3,a3_4,y1_3,a4_1,a4_2,a4_3,a4_4, y1_4);
        #16
        $display("-------------------------Ejercicio 2-----------------------------");
        $display("| \t---Ecuacion 1---\t ---Ecuacion 3---  \t\t|");
        $display("| \t----------------\t ----------------  \t\t|");
        $display("| \t  A B C D | Y   \t    A B C D | Y    \t\t|");
        $monitor("| \t  %b %b %b %b | %b   \t    %b %b %b %b | %b     \t\t|",b1_1, b1_2, b1_3, b1_4, y2_1, b3_1,b3_2,b3_3,b3_4,y2_3);
        #16
        $display("| \t---Ecuacion 2---\t ---Ecuacion 4---  \t\t|");
        $display("| \t----------------\t ----------------  \t\t|");
        $display("| \t  A B C | Y     \t   A B C | Y       \t\t|");
        $monitor("| \t  %b %b %b | %b     \t   %b %b %b | %b       \t\t|",b2_1,b2_2,b2_3,y2_2, b4_1,b4_2,b4_3,y4_2);
        
    end

    initial begin// tabla 1 ej 1
        a1_1=0; a1_2=0 ; a1_3=0;
        #1 a1_3=1;
        #1 a1_2=1; a1_3=0;
        #1 a1_3=1;
        #1 a1_1=1; a1_2=0 ; a1_3=0;
        #1 a1_3=1;
        #1 a1_2=1; a1_3=0;
        #1 a1_3=1;
    end

    initial begin //tabla 2 ej 1
            a2_1=0; a2_2=0 ; a2_3=0;
        #1 a2_3=1;
        #1 a2_2=1; a2_3=0;
        #1 a2_3=1;
        #1 a2_1=1; a2_2=0 ; a2_3=0;
        #1 a2_3=1;
        #1 a2_2=1; a2_3=0;
        #1 a2_3=1;
    end

    initial begin// tabla 3 ej 1
        #7 //se deja tiempo para que se ejecute lo de tabla 1 y 2 del ejercicio 1
        a3_1=0; a3_2=0; a3_3=0; a3_4=0;
        #1 a3_4=1;
        #1 a3_3=1; a3_4=0;
        #1 a3_4=1;
        #1 a3_2=1; a3_3=0; a3_4=0;
        #1 a3_4=1;
        #1 a3_3=1; a3_4=0;
        #1 a3_4=1;
        #1 a3_1=1; a3_2=0; a3_3=0; a3_4=0;
        #1 a3_4=1;
        #1 a3_3=1; a3_4=0;
        #1 a3_4=1;
        #1 a3_2=1; a3_3=0; a3_4=0;
        #1 a3_4=1;
        #1 a3_3=1; a3_4=0;
        #1 a3_4=1; 
    end
    initial begin// tabla 4 ej 1
        #7 //se deja tiempo para que se ejecute lo de tabla 1 y 2 del ejercicio 1
        a4_1=0; a4_2=0; a4_3=0; a4_4=0;
        #1 a4_4=1;
        #1 a4_3=1; a4_4=0;
        #1 a4_4=1;
        #1 a4_2=1; a4_3=0; a4_4=0;
        #1 a4_4=1;
        #1 a4_3=1; a4_4=0;
        #1 a4_4=1;
        #1 a4_1=1; a4_2=0; a4_3=0; a4_4=0;
        #1 a4_4=1;
        #1 a4_3=1; a4_4=0;
        #1 a4_4=1;
        #1 a4_2=1; a4_3=0; a4_4=0;
        #1 a4_4=1;
        #1 a4_3=1; a4_4=0;
        #1 a4_4=1;
    end

    initial begin// ejercicio 2 ecuacion 1
       #23
        b1_1=0; b1_2=0; b1_3=0; b1_4=0;
        #1 b1_4=1;
        #1 b1_3=1; b1_4=0;
        #1 b1_4=1;
        #1 b1_2=1; b1_3=0; b1_4=0;
        #1 b1_4=1;
        #1 b1_3=1; b1_4=0;
        #1 b1_4=1;
        #1 b1_1=1; b1_2=0; b1_3=0; b1_4=0;
        #1 b1_4=1;
        #1 b1_3=1; b1_4=0;
        #1 b1_4=1;
        #1 b1_2=1; b1_3=0; b1_4=0;
        #1 b1_4=1;
        #1 b1_3=1; b1_4=0;
        #1 b1_4=1;
    end

    initial begin //ejercicio 2 ecuacion 3
        #23
        b3_1=0; b3_2=0; b3_3=0; b3_4=0;
        #1 b3_4=1;
        #1 b3_3=1; b3_4=0;
        #1 b3_4=1;
        #1 b3_2=1; b3_3=0; b3_4=0;
        #1 b3_4=1;
        #1 b3_3=1; b3_4=0;
        #1 b3_4=1;
        #1 b3_1=1; b3_2=0; b3_3=0; b3_4=0;
        #1 b3_4=1;
        #1 b3_3=1; b3_4=0;
        #1 b3_4=1;
        #1 b3_2=1; b3_3=0; b3_4=0;
        #1 b3_4=1;
        #1 b3_3=1; b3_4=0;
        #1 b3_4=1;
        
    end
    initial begin // ejercicio 2 ecuacion 2
        #39
        b2_1 =0 ; b2_2 = 0; b2_3=0 ; 
        #1 b2_3= 1;
        #1 b2_2 = 1; b2_3=0;
        #1 b2_3 = 1;
        #1 b2_1 =1 ; b2_2 = 0; b2_3=0 ; 
        #1 b2_3= 1;
        #1 b2_2 = 1; b2_3=0;
        #1 b2_3 = 1;
        
    end

    initial begin
        #39
        b4_1 =0 ; b4_2 = 0; b4_3=0 ; 
        #1 b4_3= 1;
        #1 b4_2 = 1; b4_3=0;
        #1 b4_3 = 1;
        #1 b4_1 = 1 ; b4_2 = 0; b4_3=0 ; 
        #1 b4_3= 1;
        #1 b4_2 = 1; b4_3=0;
        #1 b4_3 = 1;
        
    end
    initial begin
        $dumpfile("modulos_tb.vcd");
        $dumpvars(0,testbench);
    end
    initial #47 $finish;
endmodule

lab04/Ejercicio4/modulos_tb.vcd
$date
	Sun Aug 09 12:08:30 2020
$end
$version
	Icarus Verilog
$end
$timescale
	1ps
$end
$scope module testbench $end
$var wire 1 ! y4_2 $end
$var wire 1 " y2_3 $end
$var wire 1 # y2_2 $end
$var wire 1 $ y2_1 $end
$var wire 1 % y1_4 $end
$var wire 1 & y1_3 $end
$var wire 1 ' y1_2 $end
$var wire 1 ( y1_1 $end
$var reg 1 ) a1_1 $end
$var reg 1 * a1_2 $end
$var reg 1 + a1_3 $end
$var reg 1 , a2_1 $end
$var reg 1 - a2_2 $end
$var reg 1 . a2_3 $end
$var reg 1 / a3_1 $end
$var reg 1 0 a3_2 $end
$var reg 1 1 a3_3 $end
$var reg 1 2 a3_4 $end
$var reg 1 3 a4_1 $end
$var reg 1 4 a4_2 $end
$var reg 1 5 a4_3 $end
$var reg 1 6 a4_4 $end
$var reg 1 7 b1_1 $end
$var reg 1 8 b1_2 $end
$var reg 1 9 b1_3 $end
$var reg 1 : b1_4 $end
$var reg 1 ; b2_1 $end
$var reg 1 < b2_2 $end
$var reg 1 = b2_3 $end
$var reg 1 > b3_1 $end
$var reg 1 ? b3_2 $end
$var reg 1 @ b3_3 $end
$var reg 1 A b3_4 $end
$var reg 1 B b4_1 $end
$var reg 1 C b4_2 $end
$var reg 1 D b4_3 $end
$scope module Ecua1 $end
$var wire 1 7 a $end
$var wire 1 8 b $end
$var wire 1 9 c $end
$var wire 1 : d $end
$var wire 1 E w1 $end
$var wire 1 F w2 $end
$var wire 1 G w3 $end
$var wire 1 H w4 $end
$var wire 1 $ y $end
$upscope $end
$scope module Ecua2 $end
$var wire 1 ; a $end
$var wire 1 < b $end
$var wire 1 = c $end
$var wire 1 # y $end
$upscope $end
$scope module Ecua3 $end
$var wire 1 > a $end
$var wire 1 ? b $end
$var wire 1 @ c $end
$var wire 1 A d $end
$var wire 1 I w1 $end
$var wire 1 J w2 $end
$var wire 1 " y $end
$upscope $end
$scope module Ecua4 $end
$var wire 1 B a $end
$var wire 1 C b $end
$var wire 1 D c $end
$var wire 1 ! y $end
$upscope $end
$scope module Tabla1 $end
$var wire 1 ) a $end
$var wire 1 * b $end
$var wire 1 + c $end
$var wire 1 K notA $end
$var wire 1 L notB $end
$var wire 1 M notC $end
$var wire 1 N w1 $end
$var wire 1 O w2 $end
$var wire 1 P w3 $end
$var wire 1 ( y $end
$upscope $end
$scope module Tabla2 $end
$var wire 1 , a $end
$var wire 1 - b $end
$var wire 1 . c $end
$var wire 1 ' y $end
$upscope $end
$scope module Tabla3 $end
$var wire 1 / a $end
$var wire 1 0 b $end
$var wire 1 1 c $end
$var wire 1 2 d $end
$var wire 1 Q notA $end
$var wire 1 R notB $end
$var wire 1 S notC $end
$var wire 1 T notD $end
$var wire 1 U w1 $end
$var wire 1 V w2 $end
$var wire 1 W w3 $end
$var wire 1 X w4 $end
$var wire 1 Y w5 $end
$var wire 1 Z w6 $end
$var wire 1 [ w7 $end
$var wire 1 \ w8 $end
$var wire 1 & y $end
$upscope $end
$scope module Tabla4 $end
$var wire 1 3 a $end
$var wire 1 4 b $end
$var wire 1 5 c $end
$var wire 1 6 d $end
$var wire 1 ] notC $end
$var wire 1 ^ notD $end
$var wire 1 _ w1 $end
$var wire 1 ` w2 $end
$var wire 1 a w3 $end
$var wire 1 % y $end
$upscope $end
$upscope $end
$enddefinitions $end
#0
$dumpvars
xa
x`
x_
x^
x]
x\
x[
xZ
xY
xX
xW
xV
xU
xT
xS
xR
xQ
0P
0O
1N
1M
1L
1K
xJ
xI
xH
xG
xF
xE
xD
xC
xB
xA
x@
x?
x>
x=
x<
x;
x:
x9
x8
x7
x6
x5
x4
x3
x2
x1
x0
x/
0.
0-
0,
0+
0*
0)
1(
1'
x&
x%
x$
x#
x"
x!
$end
#1
0(
0N
0M
1.
1+
#2
1(
1N
0'
1M
0L
0.
1-
0+
1*
#3
0(
0N
0M
1.
1+
#4
1(
1O
1'
1M
1L
0K
0.
0-
1,
0+
0*
1)
#5
0M
1P
1.
1+
#6
0(
0O
0'
1M
0P
0L
0.
1-
0+
1*
#7
1&
1(
0%
1U
0M
1P
1^
1]
0_
0`
0a
1T
1S
0Y
1R
0W
0[
1Q
0V
0X
0Z
0\
1.
1+
06
05
04
03
02
01
00
0/
#8
0&
0U
0^
0T
16
12
#9
1^
0]
1T
0S
06
15
02
11
#10
1&
0^
0T
1Y
16
12
#11
0&
1^
1]
1T
1S
0Y
0R
06
05
14
02
01
10
#12
1&
0^
0T
1W
16
12
#13
1&
1[
1^
0]
1T
0W
0S
06
15
02
11
#14
0&
0[
0^
0T
16
12
#15
1%
1a
1^
1]
1T
1S
1R
0Q
06
05
04
13
02
01
00
1/
#16
0%
1&
0a
0^
0T
1X
16
12
#17
1&
1%
1\
1^
0]
1_
1T
0X
0S
06
15
02
11
#18
0&
0\
0^
0T
16
12
#19
1&
1a
1V
1^
1]
0_
1`
1T
1S
0R
06
05
14
02
01
10
#20
0&
0a
0V
0^
0T
16
12
#21
1^
0]
1_
1T
0S
06
15
02
11
#22
1&
0^
0T
1Z
16
12
#23
0"
1$
1H
0I
0J
0E
0F
0G
0A
0@
0?
0>
0:
09
08
07
#24
1"
0$
0H
1I
1A
1:
#25
0"
0I
0A
1@
0:
19
#26
1A
1:
#27
1"
0A
0@
1?
0:
09
18
#28
1I
1A
1:
#29
0I
0A
1@
0:
19
#30
1A
1:
#31
1$
0"
1G
1H
1E
1F
0A
0@
0?
1>
0:
09
08
17
#32
1"
0G
0H
1I
1J
1A
1:
#33
0"
1G
0E
0I
0J
0A
1@
0:
19
#34
1"
0G
1J
1A
1:
#35
1G
1E
0F
0J
0A
0@
1?
0:
09
18
#36
0G
1I
1J
1A
1:
#37
1G
0E
0I
0J
0A
1@
0:
19
#38
0$
0G
1J
1A
1:
#39
1!
1#
0D
0C
0B
0=
0<
0;
#40
0!
1D
1=
#41
1!
0#
0D
1C
0=
1<
#42
1#
1D
1=
#43
0!
0D
0C
1B
0=
0<
1;
#44
1D
1=
#45
1!
0#
0D
1C
0=
1<
#46
1#
1D
1=
